optisplit/__init__.py
optisplit/cv_balance.py
optisplit-0.2.dist-info/LICENCE.txt
optisplit-0.2.dist-info/METADATA
optisplit-0.2.dist-info/WHEEL
optisplit-0.2.dist-info/top_level.txt
optisplit-0.2.dist-info/RECORD
