Metadata-Version: 2.1
Name: optisplit
Version: 0.2
Summary: An algorithm for stratified multilabel cross validation
Home-page: https://github.com/xtixtixt/optisplit
Author-email: xtixtixt@cs.helsinki.fi
License: UNKNOWN
Platform: UNKNOWN
Classifier: Programming Language :: Python :: 3
Classifier: License :: OSI Approved :: MIT License
Classifier: Operating System :: OS Independent
Requires-Python: >=3.6
License-File: LICENCE.txt
Requires-Dist: numpy
Requires-Dist: scipy
